Metadata-Version: 2.2
Name: biobb_pytorch
Version: 5.2.0
Summary: biobb_pytorch is the Biobb module collection to create and train ML & DL models.
Home-page: https://github.com/bioexcel/biobb_pytorch
Author: Biobb developers
Author-email: pieter.zanders@bsc.es
Project-URL: Documentation, http://biobb-autoencoders.readthedocs.io/en/latest/
Project-URL: Bioexcel, https://bioexcel.eu/
Keywords: Bioinformatics Workflows BioExcel Compatibility
Classifier: Development Status :: 5 - Production/Stable
Classifier: Programming Language :: Python :: 3.10
Classifier: Programming Language :: Python :: 3.11
Classifier: Programming Language :: Python :: 3.12
Classifier: License :: OSI Approved :: Apache Software License
Classifier: Operating System :: MacOS :: MacOS X
Classifier: Operating System :: POSIX
Classifier: Operating System :: Unix
Requires-Python: >=3.10
License-File: LICENSE
Requires-Dist: biobb_common==5.2.0
Requires-Dist: torch==2.3.0
Requires-Dist: lightning==2.5.0
Requires-Dist: mlcolvar==1.3.0
Requires-Dist: mdtraj
Dynamic: author
Dynamic: author-email
Dynamic: classifier
Dynamic: description
Dynamic: description-content-type
Dynamic: home-page
Dynamic: keywords
Dynamic: project-url
Dynamic: requires-dist
Dynamic: requires-python
Dynamic: summary
